awslabs/__init__.py
awslabs/mcp_nova_canvas_expert/__init__.py
awslabs/mcp_nova_canvas_expert/consts.py
awslabs/mcp_nova_canvas_expert/models.py
awslabs/mcp_nova_canvas_expert/novacanvas.py
awslabs/mcp_nova_canvas_expert/server.py
awslabs_mcp_nova_canvas_expert-0.1.311709.dist-info/METADATA
awslabs_mcp_nova_canvas_expert-0.1.311709.dist-info/WHEEL
awslabs_mcp_nova_canvas_expert-0.1.311709.dist-info/entry_points.txt
awslabs_mcp_nova_canvas_expert-0.1.311709.dist-info/RECORD
